autopypi/__init__.py
autopypi/autopypi.py
auto_pypi_setup-1.0.0.dist-info/LICENSE
auto_pypi_setup-1.0.0.dist-info/METADATA
auto_pypi_setup-1.0.0.dist-info/WHEEL
auto_pypi_setup-1.0.0.dist-info/entry_points.txt
auto_pypi_setup-1.0.0.dist-info/top_level.txt
auto_pypi_setup-1.0.0.dist-info/RECORD
