Metadata-Version: 2.1
Name: auto-pypi-setup
Version: 1.0.0
Summary: A Python command line tool to automatically setup and upload your package to PyPi. 
Home-page: https://github.com/Listen180/autopip
Author: Sen LEI
Author-email: sen.lei@outlook.com
License: BSD 3-clause
Keywords: python,package,pypi,shell,pip,clt,cli,tools,auto
Classifier: Development Status :: 3 - Alpha
Classifier: Programming Language :: Python :: 3.8
Classifier: License :: OSI Approved :: BSD License
Classifier: Operating System :: OS Independent
License-File: LICENSE
Requires-Dist: click
